xsam/__init__.py
xsam/aggregation.py
xsam/constants.py
xsam/input.py
xsam/logger.py
xsam/main.py
xsam/output.py
xsam/utilities.py
xsam/charts/app.py
xsam/charts/config.py
xsam/charts/plot_types/__init__.py
xsam/charts/plot_types/distribution.py
xsam/charts/plot_types/dual_axis_line.py
xsam/charts/plot_types/efficient_frontier_time.py
xsam/charts/plot_types/line.py
xsam/charts/plot_types/regression_scatter.py
xsam/mbs/__init__.py
xsam/mbs/mock_data.py
xsam/mbs/stochastic_processes.py
xsam/mbs/value_model.py
xsam/mbs/value_model_eval.py
xsam/mbs/value_model_main.py
xsam-0.1.14.dist-info/METADATA
xsam-0.1.14.dist-info/WHEEL
xsam-0.1.14.dist-info/entry_points.txt
xsam-0.1.14.dist-info/licenses/LICENSE
xsam-0.1.14.dist-info/RECORD
