Metadata-Version: 2.4
Name: xsam
Version: 0.1.14
Summary: XSAM assistant
Project-URL: homepage, https://pypi.org/project/xsam/
Project-URL: repository, https://github.com/stabilefrisur/xsam.git
Author-email: Stabile Frisur <stabilefrisur@proton.me>
License-Expression: MIT
License-File: LICENSE
Classifier: Development Status :: 3 - Alpha
Classifier: Intended Audience :: Developers
Classifier: License :: OSI Approved :: MIT License
Classifier: Programming Language :: Python :: 3.10
Classifier: Programming Language :: Python :: 3.11
Classifier: Programming Language :: Python :: 3.12
Classifier: Programming Language :: Python :: 3.13
Requires-Python: >=3.10
Requires-Dist: attrs>=25.3.0
Requires-Dist: dash-bootstrap-components>=2.0.1
Requires-Dist: dash>=3.0.3
Requires-Dist: matplotlib>=3.10.0
Requires-Dist: pandas[computation,excel,output-formatting,performance,plot]>=2.2.3
Requires-Dist: plotly>=6.0.1
Requires-Dist: scikit-learn>=1.6.1
Requires-Dist: statsmodels>=0.14.4
